CHANGES.txt
COPYRIGHT.txt
LICENSE.txt
README.txt
bootstrap.py
buildout.cfg
setup.py
src/z3c/__init__.py
src/z3c.macroviewlet.egg-info/PKG-INFO
src/z3c.macroviewlet.egg-info/SOURCES.txt
src/z3c.macroviewlet.egg-info/dependency_links.txt
src/z3c.macroviewlet.egg-info/namespace_packages.txt
src/z3c.macroviewlet.egg-info/not-zip-safe
src/z3c.macroviewlet.egg-info/requires.txt
src/z3c.macroviewlet.egg-info/top_level.txt
src/z3c/macroviewlet/README.txt
src/z3c/macroviewlet/__init__.py
src/z3c/macroviewlet/configure.zcml
src/z3c/macroviewlet/meta.zcml
src/z3c/macroviewlet/tests.py
src/z3c/macroviewlet/zcml.py